README.rst
setup.py
ifolder/__init__.py
ifolder/__version__.py
ifolder/recv.py
ifolder/send.py
ifolder/socketTransfering.py
ifolder/test.py
ifolder.egg-info/PKG-INFO
ifolder.egg-info/SOURCES.txt
ifolder.egg-info/dependency_links.txt
ifolder.egg-info/requires.txt
ifolder.egg-info/top_level.txt