Metadata-Version: 1.2
Name: ifolder
Version: 1.5.4
Summary: ifolder is a python package for transferring files and folders with tcp socket
Home-page: https://github.com/vincent770/ifolder.git
Author: vinct
Author-email: vt.y@qq.com
Maintainer: vt
Maintainer-email: vt.y@qq.com
License: MIT License
Platform: all
Classifier: License :: OSI Approved :: MIT License
Classifier: Programming Language :: Python :: 3
